camply/__init__.py
camply/__main__.py
camply/_version.py
camply/cli.py
camply/exceptions.py
camply/py.typed
camply/config/__init__.py
camply/config/api_config.py
camply/config/data_columns.py
camply/config/file_config.py
camply/config/logging_config.py
camply/config/notification_config.py
camply/config/search_config.py
camply/containers/__init__.py
camply/containers/api_responses.py
camply/containers/base_container.py
camply/containers/data_containers.py
camply/containers/examples.py
camply/containers/gtc_api_responses.py
camply/containers/search_model.py
camply/containers/usedirect.py
camply/notifications/__init__.py
camply/notifications/apprise.py
camply/notifications/base_notifications.py
camply/notifications/email_notifications.py
camply/notifications/multi_provider_notifications.py
camply/notifications/ntfy.py
camply/notifications/pushbullet.py
camply/notifications/pushover.py
camply/notifications/silent_notifications.py
camply/notifications/slack.py
camply/notifications/telegram.py
camply/notifications/twilio.py
camply/notifications/webhook.py
camply/providers/__init__.py
camply/providers/base_provider.py
camply/providers/going_to_camp/__init__.py
camply/providers/going_to_camp/going_to_camp_provider.py
camply/providers/going_to_camp/rec_areas.py
camply/providers/recreation_dot_gov/__init__.py
camply/providers/recreation_dot_gov/recdotgov_camps.py
camply/providers/recreation_dot_gov/recdotgov_provider.py
camply/providers/recreation_dot_gov/recdotgov_tours.py
camply/providers/usedirect/__init__.py
camply/providers/usedirect/usedirect.py
camply/providers/usedirect/variations.py
camply/providers/xanterra/__init__.py
camply/providers/xanterra/yellowstone_lodging.py
camply/search/__init__.py
camply/search/base_search.py
camply/search/search_going_to_camp.py
camply/search/search_recreationdotgov.py
camply/search/search_usedirect.py
camply/search/search_yellowstone.py
camply/utils/__init__.py
camply/utils/api_utils.py
camply/utils/configure_camply.py
camply-0.33.1.dist-info/METADATA
camply-0.33.1.dist-info/WHEEL
camply-0.33.1.dist-info/entry_points.txt
camply-0.33.1.dist-info/licenses/LICENSE
camply-0.33.1.dist-info/RECORD
