Metadata-Version: 2.4
Name: camply
Version: 0.33.1
Summary: camply, the campsite finder 🏕
Project-URL: Changelog, https://github.com/juftin/camply/releases
Project-URL: Discussions, https://github.com/juftin/camply/discussions
Project-URL: Docker, https://hub.docker.com/r/juftin/camply
Project-URL: Documentation, https://github.com/juftin/camply#readme
Project-URL: Issues, https://github.com/juftin/camply/issues
Project-URL: Source, https://github.com/juftin/camply
Author-email: Justin Flannery <justin.flannery@juftin.com>
License-Expression: MIT
License-File: LICENSE
Keywords: camping,national-parks,outdoors,recdotgov,reservations
Classifier: Development Status :: 5 - Production/Stable
Classifier: License :: OSI Approved :: MIT License
Classifier: Operating System :: OS Independent
Classifier: Programming Language :: Python :: 3
Classifier: Programming Language :: Python :: 3.9
Classifier: Programming Language :: Python :: 3.10
Classifier: Programming Language :: Python :: 3.11
Classifier: Programming Language :: Python :: 3.12
Classifier: Programming Language :: Python :: 3.13
Requires-Python: <4,>=3.9
Requires-Dist: click~=8.1.3
Requires-Dist: fake-useragent~=1.4.0
Requires-Dist: pandas<3,>=2
Requires-Dist: pydantic~=1.10.22
Requires-Dist: python-dotenv~=1.0.0
Requires-Dist: pytz~=2023.2
Requires-Dist: pyyaml~=6.0
Requires-Dist: ratelimit~=2.2.1
Requires-Dist: requests~=2.31.0
Requires-Dist: rich-click~=1.6.1
Requires-Dist: rich~=13.3.2
Requires-Dist: tenacity~=8.2.2
Provides-Extra: all
Requires-Dist: apprise~=1.3.0; extra == 'all'
Requires-Dist: trogon~=0.4.0; extra == 'all'
Requires-Dist: twilio~=7.17.0; extra == 'all'
Provides-Extra: apprise
Requires-Dist: apprise~=1.3.0; extra == 'apprise'
Provides-Extra: tui
Requires-Dist: trogon~=0.4.0; extra == 'tui'
Provides-Extra: twilio
Requires-Dist: twilio~=7.17.0; extra == 'twilio'
